pydantic_cli/__init__.py
pydantic_cli/_version.py
pydantic_cli/argparse.py
pydantic_cli/core.py
pydantic_cli/py.typed
pydantic_cli/shell_completion.py
pydantic_cli/utils.py
pydantic_cli/examples/__init__.py
pydantic_cli/examples/simple.py
pydantic_cli/examples/simple_schema.py
pydantic_cli/examples/simple_with_boolean.py
pydantic_cli/examples/simple_with_boolean_and_config.py
pydantic_cli/examples/simple_with_boolean_custom.py
pydantic_cli/examples/simple_with_custom.py
pydantic_cli/examples/simple_with_custom_and_setup_log.py
pydantic_cli/examples/simple_with_enum.py
pydantic_cli/examples/simple_with_enum_by_name.py
pydantic_cli/examples/simple_with_json_config.py
pydantic_cli/examples/simple_with_json_config_not_found.py
pydantic_cli/examples/simple_with_list.py
pydantic_cli/examples/simple_with_shell_autocomplete_support.py
pydantic_cli/examples/subparser.py
pydantic_cli/tests/__init__.py
pydantic_cli/tests/test_examples_simple.py
pydantic_cli/tests/test_examples_simple_boolean_and_config.py
pydantic_cli/tests/test_examples_simple_schema.py
pydantic_cli/tests/test_examples_simple_with_boolean.py
pydantic_cli/tests/test_examples_simple_with_boolean_custom.py
pydantic_cli/tests/test_examples_simple_with_custom.py
pydantic_cli/tests/test_examples_simple_with_custom_and_setup_log.py
pydantic_cli/tests/test_examples_simple_with_enum.py
pydantic_cli/tests/test_examples_simple_with_enum_by_name.py
pydantic_cli/tests/test_examples_simple_with_json_config_and_env.py
pydantic_cli/tests/test_examples_simple_with_json_config_not_found.py
pydantic_cli/tests/test_examples_simple_with_list.py
pydantic_cli/tests/test_examples_simple_with_shell_autocomplete_support.py
pydantic_cli/tests/test_examples_subparser.py
pydantic_cli/tests/test_examples_with_json_config.py
pydantic_cli-10.0.0.dist-info/METADATA
pydantic_cli-10.0.0.dist-info/WHEEL
pydantic_cli-10.0.0.dist-info/licenses/LICENSE
pydantic_cli-10.0.0.dist-info/RECORD
