Metadata-Version: 2.4
Name: pydantic_cli
Version: 10.0.0
Summary: Turn Pydantic defined Data Models into CLI Tools
Project-URL: Source Code, http://github.com/mpkocher/pydantic-cli
Author-email: "M. Kocher" <michael.kocher@me.com>
License: MIT License
License-File: LICENSE
Classifier: License :: OSI Approved :: MIT License
Classifier: Operating System :: OS Independent
Classifier: Programming Language :: Python :: 3
Classifier: Programming Language :: Python :: 3.10
Classifier: Programming Language :: Python :: 3.11
Classifier: Programming Language :: Python :: 3.12
Classifier: Programming Language :: Python :: 3.13
Classifier: Programming Language :: Python :: 3.14
Classifier: Topic :: Software Development
Classifier: Topic :: Utilities
Classifier: Typing :: Typed
Requires-Python: >=3.10
Requires-Dist: pydantic>=2.8.2
Provides-Extra: shtab
Requires-Dist: shtab>=1.3.1; extra == 'shtab'
Provides-Extra: test
Requires-Dist: black>=24.4.2; extra == 'test'
Requires-Dist: mypy>=1.10.1; extra == 'test'
Requires-Dist: pytest-cov>=4.0.0; extra == 'test'
Requires-Dist: pytest>=8.2.2; extra == 'test'
